package com.tom.core.util;

public class SystemConnector
{
  /* Error */
  public static void doConnect(String data)
    throws java.lang.Exception
  {
    // Byte code:
    //   0: new 19	java/lang/StringBuilder
    //   3: dup
    //   4: ldc 21
    //   6: invokespecial 23	java/lang/StringBuilder:<init>	(Ljava/lang/String;)V
    //   9: aload_0
    //   10: invokevirtual 25	java/lang/StringBuilder:append	(Ljava/lang/String;)Ljava/lang/StringBuilder;
    //   13: invokevirtual 29	java/lang/StringBuilder:toString	()Ljava/lang/String;
    //   16: astore_1
    //   17: new 33	java/net/URL
    //   20: dup
    //   21: ldc 35
    //   23: invokespecial 37	java/net/URL:<init>	(Ljava/lang/String;)V
    //   26: astore_2
    //   27: aload_2
    //   28: invokevirtual 38	java/net/URL:openConnection	()Ljava/net/URLConnection;
    //   31: astore_3
    //   32: aload_3
    //   33: checkcast 42	java/net/HttpURLConnection
    //   36: astore 4
    //   38: aload 4
    //   40: iconst_1
    //   41: invokevirtual 44	java/net/HttpURLConnection:setDoOutput	(Z)V
    //   44: aload 4
    //   46: ldc 48
    //   48: invokevirtual 50	java/net/HttpURLConnection:setRequestMethod	(Ljava/lang/String;)V
    //   51: aload 4
    //   53: ldc 53
    //   55: ldc 55
    //   57: invokevirtual 57	java/net/HttpURLConnection:setRequestProperty	(Ljava/lang/String;Ljava/lang/String;)V
    //   60: aload 4
    //   62: ldc 61
    //   64: ldc 63
    //   66: invokevirtual 57	java/net/HttpURLConnection:setRequestProperty	(Ljava/lang/String;Ljava/lang/String;)V
    //   69: aload 4
    //   71: ldc 65
    //   73: aload_1
    //   74: invokevirtual 67	java/lang/String:length	()I
    //   77: invokestatic 73	java/lang/String:valueOf	(I)Ljava/lang/String;
    //   80: invokevirtual 57	java/net/HttpURLConnection:setRequestProperty	(Ljava/lang/String;Ljava/lang/String;)V
    //   83: aconst_null
    //   84: astore 5
    //   86: aconst_null
    //   87: astore 6
    //   89: aconst_null
    //   90: astore 7
    //   92: aconst_null
    //   93: astore 8
    //   95: aconst_null
    //   96: astore 9
    //   98: new 77	java/lang/StringBuffer
    //   101: dup
    //   102: invokespecial 79	java/lang/StringBuffer:<init>	()V
    //   105: astore 10
    //   107: aconst_null
    //   108: astore 11
    //   110: aload 4
    //   112: invokevirtual 80	java/net/HttpURLConnection:getOutputStream	()Ljava/io/OutputStream;
    //   115: astore 5
    //   117: new 84	java/io/OutputStreamWriter
    //   120: dup
    //   121: aload 5
    //   123: invokespecial 86	java/io/OutputStreamWriter:<init>	(Ljava/io/OutputStream;)V
    //   126: astore 6
    //   128: aload 6
    //   130: aload_1
    //   131: invokevirtual 89	java/lang/String:toString	()Ljava/lang/String;
    //   134: invokevirtual 90	java/io/OutputStreamWriter:write	(Ljava/lang/String;)V
    //   137: aload 6
    //   139: invokevirtual 93	java/io/OutputStreamWriter:flush	()V
    //   142: aload 4
    //   144: invokevirtual 96	java/net/HttpURLConnection:getResponseCode	()I
    //   147: sipush 300
    //   150: if_icmplt +31 -> 181
    //   153: new 17	java/lang/Exception
    //   156: dup
    //   157: new 19	java/lang/StringBuilder
    //   160: dup
    //   161: ldc 99
    //   163: invokespecial 23	java/lang/StringBuilder:<init>	(Ljava/lang/String;)V
    //   166: aload 4
    //   168: invokevirtual 96	java/net/HttpURLConnection:getResponseCode	()I
    //   171: invokevirtual 101	java/lang/StringBuilder:append	(I)Ljava/lang/StringBuilder;
    //   174: invokevirtual 29	java/lang/StringBuilder:toString	()Ljava/lang/String;
    //   177: invokespecial 104	java/lang/Exception:<init>	(Ljava/lang/String;)V
    //   180: athrow
    //   181: aload 4
    //   183: invokevirtual 105	java/net/HttpURLConnection:getInputStream	()Ljava/io/InputStream;
    //   186: astore 7
    //   188: new 109	java/io/InputStreamReader
    //   191: dup
    //   192: aload 7
    //   194: invokespecial 111	java/io/InputStreamReader:<init>	(Ljava/io/InputStream;)V
    //   197: astore 8
    //   199: new 114	java/io/BufferedReader
    //   202: dup
    //   203: aload 8
    //   205: invokespecial 116	java/io/BufferedReader:<init>	(Ljava/io/Reader;)V
    //   208: astore 9
    //   210: goto +11 -> 221
    //   213: aload 10
    //   215: aload 11
    //   217: invokevirtual 119	java/lang/StringBuffer:append	(Ljava/lang/String;)Ljava/lang/StringBuffer;
    //   220: pop
    //   221: aload 9
    //   223: invokevirtual 122	java/io/BufferedReader:readLine	()Ljava/lang/String;
    //   226: dup
    //   227: astore 11
    //   229: ifnonnull -16 -> 213
    //   232: goto +58 -> 290
    //   235: astore 12
    //   237: aload 6
    //   239: ifnull +8 -> 247
    //   242: aload 6
    //   244: invokevirtual 125	java/io/OutputStreamWriter:close	()V
    //   247: aload 5
    //   249: ifnull +8 -> 257
    //   252: aload 5
    //   254: invokevirtual 128	java/io/OutputStream:close	()V
    //   257: aload 9
    //   259: ifnull +8 -> 267
    //   262: aload 9
    //   264: invokevirtual 131	java/io/BufferedReader:close	()V
    //   267: aload 8
    //   269: ifnull +8 -> 277
    //   272: aload 8
    //   274: invokevirtual 132	java/io/InputStreamReader:close	()V
    //   277: aload 7
    //   279: ifnull +8 -> 287
    //   282: aload 7
    //   284: invokevirtual 133	java/io/InputStream:close	()V
    //   287: aload 12
    //   289: athrow
    //   290: aload 6
    //   292: ifnull +8 -> 300
    //   295: aload 6
    //   297: invokevirtual 125	java/io/OutputStreamWriter:close	()V
    //   300: aload 5
    //   302: ifnull +8 -> 310
    //   305: aload 5
    //   307: invokevirtual 128	java/io/OutputStream:close	()V
    //   310: aload 9
    //   312: ifnull +8 -> 320
    //   315: aload 9
    //   317: invokevirtual 131	java/io/BufferedReader:close	()V
    //   320: aload 8
    //   322: ifnull +8 -> 330
    //   325: aload 8
    //   327: invokevirtual 132	java/io/InputStreamReader:close	()V
    //   330: aload 7
    //   332: ifnull +8 -> 340
    //   335: aload 7
    //   337: invokevirtual 133	java/io/InputStream:close	()V
    //   340: return
    // Line number table:
    //   Java source line #16	-> byte code offset #0
    //   Java source line #18	-> byte code offset #17
    //   Java source line #19	-> byte code offset #27
    //   Java source line #20	-> byte code offset #32
    //   Java source line #22	-> byte code offset #38
    //   Java source line #23	-> byte code offset #44
    //   Java source line #24	-> byte code offset #51
    //   Java source line #25	-> byte code offset #60
    //   Java source line #26	-> byte code offset #69
    //   Java source line #28	-> byte code offset #83
    //   Java source line #29	-> byte code offset #86
    //   Java source line #30	-> byte code offset #89
    //   Java source line #31	-> byte code offset #92
    //   Java source line #32	-> byte code offset #95
    //   Java source line #33	-> byte code offset #98
    //   Java source line #34	-> byte code offset #107
    //   Java source line #37	-> byte code offset #110
    //   Java source line #38	-> byte code offset #117
    //   Java source line #40	-> byte code offset #128
    //   Java source line #41	-> byte code offset #137
    //   Java source line #43	-> byte code offset #142
    //   Java source line #44	-> byte code offset #153
    //   Java source line #47	-> byte code offset #181
    //   Java source line #48	-> byte code offset #188
    //   Java source line #49	-> byte code offset #199
    //   Java source line #51	-> byte code offset #210
    //   Java source line #52	-> byte code offset #213
    //   Java source line #51	-> byte code offset #221
    //   Java source line #55	-> byte code offset #235
    //   Java source line #56	-> byte code offset #237
    //   Java source line #57	-> byte code offset #242
    //   Java source line #59	-> byte code offset #247
    //   Java source line #60	-> byte code offset #252
    //   Java source line #62	-> byte code offset #257
    //   Java source line #63	-> byte code offset #262
    //   Java source line #65	-> byte code offset #267
    //   Java source line #66	-> byte code offset #272
    //   Java source line #68	-> byte code offset #277
    //   Java source line #69	-> byte code offset #282
    //   Java source line #71	-> byte code offset #287
    //   Java source line #56	-> byte code offset #290
    //   Java source line #57	-> byte code offset #295
    //   Java source line #59	-> byte code offset #300
    //   Java source line #60	-> byte code offset #305
    //   Java source line #62	-> byte code offset #310
    //   Java source line #63	-> byte code offset #315
    //   Java source line #65	-> byte code offset #320
    //   Java source line #66	-> byte code offset #325
    //   Java source line #68	-> byte code offset #330
    //   Java source line #69	-> byte code offset #335
    //   Java source line #75	-> byte code offset #340
    // Local variable table:
    //   start	length	slot	name	signature
    //   0	341	0	data	String
    //   16	115	1	parameterData	String
    //   26	2	2	localURL	java.net.URL
    //   31	2	3	connection	java.net.URLConnection
    //   36	146	4	httpURLConnection	java.net.HttpURLConnection
    //   84	222	5	outputStream	java.io.OutputStream
    //   87	209	6	outputStreamWriter	java.io.OutputStreamWriter
    //   90	246	7	inputStream	java.io.InputStream
    //   93	233	8	inputStreamReader	java.io.InputStreamReader
    //   96	220	9	reader	java.io.BufferedReader
    //   105	109	10	resultBuffer	StringBuffer
    //   108	120	11	tempLine	String
    //   235	53	12	localObject	Object
    // Exception table:
    //   from	to	target	type
    //   110	235	235	finally
  }
}
